{"chunk_definitions":[{"chunk_id":"cfpzob6g8xnpf","chunk_label":"unnamed-chunk-1","document_id":"E71099F1","expansion_state":0,"options":{"engine":"r","label":"unnamed-chunk-6"},"row":8,"row_count":1,"visible":true},{"chunk_id":"c4s6x11q2iucg","chunk_label":"unnamed-chunk-2","document_id":"E71099F1","expansion_state":0,"options":{"engine":"r","label":"unnamed-chunk-3"},"row":16,"row_count":1,"visible":true},{"chunk_id":"c44509yq0zrml","chunk_label":"unnamed-chunk-3","document_id":"E71099F1","expansion_state":0,"options":{"engine":"r","label":"unnamed-chunk-3"},"row":21,"row_count":1,"visible":true},{"chunk_id":"colgrv0da6p70","chunk_label":"unnamed-chunk-4","document_id":"E71099F1","expansion_state":0,"options":{"engine":"r","label":"unnamed-chunk-10"},"row":27,"row_count":1,"visible":true},{"chunk_id":"cimobs829q8x1","chunk_label":"unnamed-chunk-5","document_id":"E71099F1","expansion_state":0,"options":{"engine":"r","label":"unnamed-chunk-4"},"row":31,"row_count":1,"visible":true},{"chunk_id":"csbkchzoh64wy","chunk_label":"unnamed-chunk-6","document_id":"E71099F1","expansion_state":0,"options":{"engine":"r","label":"unnamed-chunk-6"},"row":37,"row_count":1,"visible":true},{"chunk_id":"cflpiz035n3br","chunk_label":"unnamed-chunk-7","document_id":"E71099F1","expansion_state":0,"options":{"engine":"r","label":"unnamed-chunk-1"},"row":41,"row_count":1,"visible":true},{"chunk_id":"c7l48pbwtd63q","chunk_label":"unnamed-chunk-8","document_id":"E71099F1","expansion_state":0,"options":{"engine":"r","label":"unnamed-chunk-2"},"row":45,"row_count":1,"visible":true}],"doc_write_time":1570444353}